APIactModule/__init__.py
APIactModule/main.py
APIactModule-1.4.6.dist-info/LICENSE
APIactModule-1.4.6.dist-info/METADATA
APIactModule-1.4.6.dist-info/WHEEL
APIactModule-1.4.6.dist-info/top_level.txt
APIactModule-1.4.6.dist-info/RECORD
