Metadata-Version: 2.1
Name: APIactModule
Version: 1.4.6
Home-page: https://github.com/siraisi368/APIActionModule
Download-URL: https://github.com/siraisi368/APIActionModule
Author: MasatoSiraisi
License: Apache License2.0
License-File: LICENSE
Requires-Dist: requests
Requires-Dist: ntplib
Requires-Dist: xmltodict
